beaver_ai/__init__.py
beaver_ai/chat.py
beaver_ai/client.py
beaver_ai/errors.py
beaver_ai/types.py
beaver_ai-0.1.0.dist-info/METADATA
beaver_ai-0.1.0.dist-info/WHEEL
beaver_ai-0.1.0.dist-info/top_level.txt
beaver_ai-0.1.0.dist-info/RECORD
