Metadata-Version: 2.4
Name: beaver-ai
Version: 0.1.0
Summary: Python SDK for the Beaver AI Gateway
Requires-Python: >=3.8
Requires-Dist: requests>=2.25.0
